pixelemon/__init__.py
pixelemon/_plate_solve.py
pixelemon/_telescope.py
pixelemon/_telescope_image.py
pixelemon/constants.py
pixelemon/logging.py
pixelemon/py.typed
pixelemon/correlation/__init__.py
pixelemon/correlation/_candidates.py
pixelemon/correlation/_correlated_detection.py
pixelemon/correlation/_correlation_settings.py
pixelemon/optics/__init__.py
pixelemon/optics/_arducam_cs2316zm02.py
pixelemon/optics/_arducam_cs2325zm01.py
pixelemon/optics/_arducam_m2508zh02.py
pixelemon/optics/_base_optical_assembly.py
pixelemon/optics/_goshyda_35.py
pixelemon/optics/_williams_mini_cat_51.py
pixelemon/processing/__init__.py
pixelemon/processing/_background_settings.py
pixelemon/processing/_detection.py
pixelemon/processing/_detection_settings.py
pixelemon/sensors/__init__.py
pixelemon/sensors/_base_sensor.py
pixelemon/sensors/_imx_174.py
pixelemon/sensors/_imx_296.py
pixelemon-0.5.0.dist-info/METADATA
pixelemon-0.5.0.dist-info/WHEEL
pixelemon-0.5.0.dist-info/RECORD
