Metadata-Version: 2.4
Name: pixelemon
Version: 0.5.0
Summary: Citra's basic image processing package
Author-email: Brandon Sexton <brandon@citra.space>
License-Expression: MIT
Requires-Python: <3.13,>=3.9
Requires-Dist: astropy
Requires-Dist: cedar-solve
Requires-Dist: keplemon
Requires-Dist: pydantic
Requires-Dist: sep
Provides-Extra: build
Requires-Dist: build; extra == 'build'
Provides-Extra: deploy
Requires-Dist: twine; extra == 'deploy'
Provides-Extra: dev
Requires-Dist: black; extra == 'dev'
Requires-Dist: flake8; extra == 'dev'
Requires-Dist: flake8-pytest-style; extra == 'dev'
Requires-Dist: isort; extra == 'dev'
Requires-Dist: mockito; extra == 'dev'
Requires-Dist: mypy; extra == 'dev'
Requires-Dist: pre-commit; extra == 'dev'
Requires-Dist: pytest; extra == 'dev'
Requires-Dist: pytest-cov; extra == 'dev'
Provides-Extra: docs
Requires-Dist: sphinx; extra == 'docs'
Requires-Dist: sphinx-autodoc-typehints; extra == 'docs'
Requires-Dist: sphinx-markdown-builder; extra == 'docs'
Provides-Extra: test
Requires-Dist: mockito; extra == 'test'
Requires-Dist: pytest; extra == 'test'
Requires-Dist: pytest-cov; extra == 'test'
